cryptnoxpro/__init__.py
cryptnoxpro/config.py
cryptnoxpro/enums.py
cryptnoxpro/interactive_cli.py
cryptnoxpro/main.py
cryptnoxpro/command/__init__.py
cryptnoxpro/command/btc.py
cryptnoxpro/command/card_configuration.py
cryptnoxpro/command/cards.py
cryptnoxpro/command/change_pin.py
cryptnoxpro/command/change_puk.py
cryptnoxpro/command/command.py
cryptnoxpro/command/config.py
cryptnoxpro/command/decrypt.py
cryptnoxpro/command/eth.py
cryptnoxpro/command/factory.py
cryptnoxpro/command/get_clearpubkey.py
cryptnoxpro/command/get_xpub.py
cryptnoxpro/command/history.py
cryptnoxpro/command/info.py
cryptnoxpro/command/initialize.py
cryptnoxpro/command/reset.py
cryptnoxpro/command/seed.py
cryptnoxpro/command/server.py
cryptnoxpro/command/transfer.py
cryptnoxpro/command/unknown.py
cryptnoxpro/command/unlock_pin.py
cryptnoxpro/command/user_key.py
cryptnoxpro/command/card/__init__.py
cryptnoxpro/command/card/info.py
cryptnoxpro/command/card/initialize.py
cryptnoxpro/command/erc_token/__init__.py
cryptnoxpro/command/erc_token/contract.py
cryptnoxpro/command/erc_token/info.py
cryptnoxpro/command/erc_token/initialize.py
cryptnoxpro/command/helper/__init__.py
cryptnoxpro/command/helper/backup.py
cryptnoxpro/command/helper/cards.py
cryptnoxpro/command/helper/config.py
cryptnoxpro/command/helper/download_folder.py
cryptnoxpro/command/helper/helper_methods.py
cryptnoxpro/command/helper/notification.py
cryptnoxpro/command/helper/security.py
cryptnoxpro/command/helper/seed_backup.py
cryptnoxpro/command/helper/ui.py
cryptnoxpro/command/options/__init__.py
cryptnoxpro/command/options/common.py
cryptnoxpro/command/options/eth.py
cryptnoxpro/command/options/options.py
cryptnoxpro/command/user_keys/__init__.py
cryptnoxpro/command/user_keys/authentication.py
cryptnoxpro/command/user_keys/user_key_base.py
cryptnoxpro/command/user_keys/aws_kms/__init__.py
cryptnoxpro/command/user_keys/aws_kms/aws_kms.py
cryptnoxpro/command/user_keys/hello/__init__.py
cryptnoxpro-2.9.1.dist-info/licenses/LICENSE
cryptnoxpro-2.9.1.dist-info/METADATA
cryptnoxpro-2.9.1.dist-info/WHEEL
cryptnoxpro-2.9.1.dist-info/entry_points.txt
cryptnoxpro-2.9.1.dist-info/top_level.txt
cryptnoxpro-2.9.1.dist-info/RECORD
