Metadata-Version: 2.4
Name: cryptnoxpro
Version: 2.9.1
Home-page: https://www.cryptnox.com/
Author: Cryptnox SA
Author-email: info@cryptnox.ch
License: GPLv3+
Project-URL: Source Code, https://github.com/Cryptnox-Software/cryptnoxpro
Keywords: python,cryptography,bitcoin,ethereum,cleos,cryptocurrency,wallet
Platform: any
Classifier: Development Status :: 4 - Beta
Classifier: Environment :: Console
Classifier: License :: OSI Approved :: GNU General Public License v3 or later (GPLv3+)
Classifier: License :: Other/Proprietary License
Classifier: Operating System :: OS Independent
Classifier: Programming Language :: Python :: 3 :: Only
Classifier: Programming Language :: Python :: 3.7
Classifier: Programming Language :: Python :: 3.8
Classifier: Programming Language :: Python :: 3.9
Classifier: Programming Language :: Python :: 3.10
Classifier: Programming Language :: Python :: 3.11
Classifier: Programming Language :: Python :: 3.12
Classifier: Topic :: Security :: Cryptography
Requires-Python: <=3.13.7,>=3.11
License-File: LICENSE
Requires-Dist: argparse
Requires-Dist: appdirs
Requires-Dist: base58
Requires-Dist: boto3
Requires-Dist: ecdsa
Requires-Dist: colander
Requires-Dist: cryptnoxpy>=2.0.0
Requires-Dist: lazy-import
Requires-Dist: pytz
Requires-Dist: requests
Requires-Dist: tabulate
Requires-Dist: stdiomask
Requires-Dist: web3
Requires-Dist: winsdk; platform_system == "Windows"
Dynamic: description
Dynamic: license-file
